setup.py
namedropper/__init__.py
namedropper/scripts.py
namedropper/spotlight.py
namedropper/util.py
namedropper/viaf.py
namedropper.egg-info/PKG-INFO
namedropper.egg-info/SOURCES.txt
namedropper.egg-info/dependency_links.txt
namedropper.egg-info/requires.txt
namedropper.egg-info/top_level.txt
scripts/count-nametags
scripts/lookup-names
test/__init__.py
test/test_spotlight.py
test/test_util.py
test/fixtures/__init__.py
test/fixtures/hobsbaum_annotations.py
test/fixtures/ilnnames_annotations.py