Metadata-Version: 1.0
Name: namedropper
Version: 0.3.1
Summary: A collection of python utilities and scripts for identifying named entities in text and XML
Home-page: https://github.com/emory-libraries-disc/name-dropper
Author: Emory University Libraries
Author-email: libsysdev-l@listserv.cc.emory.edu
License: Apache License, Version 2.0
Platform: UNKNOWN
Classifier: Development Status :: 2 - Pre-Alpha
Classifier: Environment :: Console
Classifier: Intended Audience :: Developers
Classifier: Intended Audience :: End Users/Desktop
Classifier: Natural Language :: English
Classifier: Operating System :: OS Independent
Classifier: Programming Language :: Python
Classifier: Topic :: Software Development :: Libraries :: Python Modules
Classifier: Topic :: Utilities
